epspy/__init__.py
epspy/meps.py
epspy-1.0.0.dist-info/METADATA
epspy-1.0.0.dist-info/WHEEL
epspy-1.0.0.dist-info/licenses/LICENSE
epspy-1.0.0.dist-info/RECORD
