Metadata-Version: 2.3
Name: epspy
Version: 1.0.0
Summary: Extragalactic Point Sources
Project-URL: Repository, https://github.com/shikharmittal04/epspy.git
Author-email: Shikhar Mittal <shikhar.mittal4@gmail.com>
License: MIT License
License-File: LICENSE
Keywords: extragalactic,foregrounds,point sources
Classifier: License :: OSI Approved :: MIT License
Classifier: Natural Language :: English
Classifier: Operating System :: OS Independent
Classifier: Programming Language :: Python :: 3.8
Classifier: Programming Language :: Python :: 3.9
Classifier: Programming Language :: Python :: 3.10
Classifier: Topic :: Scientific/Engineering :: Astronomy
Requires-Python: >=3.8
Requires-Dist: healpy
Requires-Dist: mpi4py
Requires-Dist: transformcl
